kaskada/api/v1alpha/compute_pb2.py
kaskada/api/v1alpha/compute_pb2_grpc.py
kaskada/api/v1alpha/credential_pb2.py
kaskada/api/v1alpha/credential_pb2_grpc.py
kaskada/api/v1alpha/data_token_pb2.py
kaskada/api/v1alpha/data_token_pb2_grpc.py
kaskada/api/v1alpha/materialization_pb2.py
kaskada/api/v1alpha/materialization_pb2_grpc.py
kaskada/api/v1alpha/query_pb2.py
kaskada/api/v1alpha/query_pb2_grpc.py
kaskada/api/v1alpha/shared_pb2.py
kaskada/api/v1alpha/shared_pb2_grpc.py
kaskada/api/v1alpha/spec_pb2.py
kaskada/api/v1alpha/spec_pb2_grpc.py
kaskada/api/v1alpha/staged_file_pb2.py
kaskada/api/v1alpha/staged_file_pb2_grpc.py
kaskada/api/v1alpha/table_pb2.py
kaskada/api/v1alpha/table_pb2_grpc.py
kaskada/api/v1alpha/test_cases_pb2.py
kaskada/api/v1alpha/test_cases_pb2_grpc.py
kaskada/api/v1alpha/view_pb2.py
kaskada/api/v1alpha/view_pb2_grpc.py
kaskada/errdetails/v1alpha/fenl_diagnostics_pb2.py
kaskada/errdetails/v1alpha/fenl_diagnostics_pb2_grpc.py
kaskada/fenl/v1alpha/schema_pb2.py
kaskada/fenl/v1alpha/schema_pb2_grpc.py
kaskada/prepare/v1alpha/slice_pb2.py
kaskada/prepare/v1alpha/slice_pb2_grpc.py
kaskada/puffin/v1alpha/iceberg_table_pb2.py
kaskada/puffin/v1alpha/iceberg_table_pb2_grpc.py
kaskada/shared/v1alpha/catalog_pb2.py
kaskada/shared/v1alpha/catalog_pb2_grpc.py
kaskada/shared/v1alpha/options_pb2.py
kaskada/shared/v1alpha/options_pb2_grpc.py
kaskada/shared/v1alpha/request_details_pb2.py
kaskada/shared/v1alpha/request_details_pb2_grpc.py
validate/__init__.py
validate/validate_pb2.py
validate/validate_pb2_grpc.py
kaskada_grpc-0.0.18.dist-info/LICENSE
kaskada_grpc-0.0.18.dist-info/METADATA
kaskada_grpc-0.0.18.dist-info/WHEEL
kaskada_grpc-0.0.18.dist-info/top_level.txt
kaskada_grpc-0.0.18.dist-info/RECORD
