Metadata-Version: 2.1
Name: kaskada-grpc
Version: 0.0.18
Summary: Kaskada's gRPC client
Home-page: https://kaskada.com
Author: Kaskada
Author-email: support@kaskada.com
Project-URL: Documentation, https://docs.kaskada.com/
Classifier: Development Status :: 3 - Alpha
Classifier: Framework :: Jupyter
Classifier: Programming Language :: Python :: 3
Classifier: License :: Other/Proprietary License
Requires-Python: >=3.6
License-File: LICENSE
Requires-Dist: grpcio
Requires-Dist: grpcio-tools
Requires-Dist: googleapis-common-protos
Requires-Dist: protobuf
